sbtools/__init__.py
SBTools-0.0.37.dist-info/METADATA
SBTools-0.0.37.dist-info/WHEEL
SBTools-0.0.37.dist-info/top_level.txt
SBTools-0.0.37.dist-info/RECORD
